fabric_fast_start/DimensionManager.py
fabric_fast_start/FabricContext.py
fabric_fast_start/Logger.py
fabric_fast_start/__init__.py
fabric_fast_start/_helper_functions.py
fabric_fast_start/_icons.py
fabric_fast_start/main.py
fabric_fast_start/py.typed
fabric_fast_start/config/__init__.py
fabric_fast_start/config/config_resolver.py
fabric_fast_start/config/config_storage.py
fabric_fast_start/directlake/__init__.py
fabric_fast_start/directlake/_guardrails.py
fabric_fast_start/dw/__init__.py
fabric_fast_start/lakehouse/__init__.py
fabric_fast_start/lakehouse/_get_lakehouse_columns.py
fabric_fast_start/lakehouse/_get_lakehouse_tables.py
fabric_fast_start/lakehouse/_lakehouse.py
fabric_fast_start/lakehouse/_shortcuts.py
fabric_fast_start-0.1.4.dist-info/LICENSE
fabric_fast_start-0.1.4.dist-info/METADATA
fabric_fast_start-0.1.4.dist-info/WHEEL
fabric_fast_start-0.1.4.dist-info/top_level.txt
fabric_fast_start-0.1.4.dist-info/RECORD
