Metadata-Version: 2.1
Name: fabric-fast-start
Version: 0.1.4
Summary: Fabric Fast Start is a set of tools to help you get started with Fabric.
Author-email: Serge Artishev <serge.artishev@fusion5.co.nz>
Maintainer-email: Serge Artishev <serge.artishev@fusion5.co.nz>
License: MIT License
Project-URL: Homepage, https://github.com/f5serge/fabric-fast-start
Project-URL: Issues, https://github.com/f5serge/fabric-fast-start/issues
Project-URL: Contributing, https://github.com/f5serge/fabric-fast-start/pulls
Project-URL: Releases, https://github.com/f5serge/fabric-fast-start/releases
Classifier: Development Status :: 3 - Alpha
Classifier: License :: OSI Approved :: MIT License
Classifier: Operating System :: OS Independent
Classifier: Programming Language :: Python :: 3
Classifier: Programming Language :: Python :: 3.10
Classifier: Programming Language :: Python :: 3.11
Classifier: Programming Language :: Python :: 3.12
Requires-Python: >=3.10
License-File: LICENSE
Provides-Extra: dev
Requires-Dist: pre-commit; extra == "dev"
Requires-Dist: azure-core; extra == "dev"
Requires-Dist: azure-data-tables; extra == "dev"
Requires-Dist: dummy-notebookutils; extra == "dev"
Requires-Dist: ruff; extra == "dev"
Requires-Dist: black; extra == "dev"
Requires-Dist: mocker; extra == "dev"
Requires-Dist: mypy; extra == "dev"
Requires-Dist: types-PyYAML; extra == "dev"
Requires-Dist: types-requests; extra == "dev"
Requires-Dist: pandas-stubs; extra == "dev"
Requires-Dist: types-tqdm; extra == "dev"
Requires-Dist: pyspark==3.5.1; extra == "dev"
Requires-Dist: delta-spark==3.2.0; extra == "dev"
Requires-Dist: semantic-link==0.7.7; extra == "dev"
Requires-Dist: jwt==1.3.1; extra == "dev"
Provides-Extra: test
Requires-Dist: azure-core; extra == "test"
Requires-Dist: azure-data-tables; extra == "test"
Requires-Dist: azure-storage-blob; extra == "test"
Requires-Dist: dummy-notebookutils; extra == "test"
Requires-Dist: pyyaml; extra == "test"
Requires-Dist: pytest; extra == "test"
Requires-Dist: pytest-cov; extra == "test"
Requires-Dist: mocker; extra == "test"
Requires-Dist: pytest-mock; extra == "test"
Requires-Dist: types-PyYAML; extra == "test"
Requires-Dist: types-requests; extra == "test"
Requires-Dist: pandas-stubs; extra == "test"
Requires-Dist: types-tqdm; extra == "test"
Requires-Dist: pyspark==3.5.1; extra == "test"
Requires-Dist: delta-spark==3.2.0; extra == "test"
Requires-Dist: semantic-link==0.7.7; extra == "test"
Requires-Dist: jwt==1.3.1; extra == "test"
